[null,{"name":"ct","permissions":"NONE","restriction":"0","_id":"jJzpB","actions":[{"info":"1","infoIndex":"1","storage":"1","varName":"contr","name":"Store Command Params"},{"condition":"0","comparison":"3","value":"1","iftrue":"2","iftrueVal":"6","iffalse":"0","iffalseVal":"","name":"Check Parameters"},{"title":"***GTA5RP | TOXIC FAMILY***","author":"","color":"00FF3B","url":"","authorIcon":"","authorUrl":"","imageUrl":"","thumbUrl":"","timestamp":"false","debug":"false","text":"","year":"","month":"","day":"","hour":"","minute":"","second":"","storage":"1","varName":"emb1","name":"Create Embed Message"},{"storage":"1","varName":"emb1","fieldName":":x:  **В команде допущена ошибка!**","message":"Верное использование команды: *-ct <Название контракта>*","inline":"1","name":"Add Embed Field"},{"storage":"1","varName":"emb1","channel":"0","varName2":"","storage3":"0","varName3":"","iffalse":"0","iffalseVal":"","messageContent":"","name":"Send Embed Message"},{"name":"End Action Sequence"},{"title":"***GTA5RP | TOXIC FAMILY***","author":"","color":"00FF3B","url":"","authorIcon":"","authorUrl":"","imageUrl":"","thumbUrl":"","timestamp":"true","debug":"false","text":"","year":"","month":"","day":"","hour":"","minute":"","second":"","storage":"1","varName":"emb2","name":"Create Embed Message"},{"storage":"1","varName":"emb2","fieldName":"**Запрос на выплату контракта**","message":":small_orange_diamond:  Тег участника: ${member}\n:small_orange_diamond:  Выполненный контракт: ${tempVars(\"contr\")}\n:small_orange_diamond:  На выплату: 22.000$","inline":"1","name":"Add Embed Field"},{"storage":"1","varName":"emb2","channel":"6","varName2":"ct","storage3":"0","varName3":"","iffalse":"0","iffalseVal":"","messageContent":"<@&916785415988600832>","name":"Send Embed Message"},{"storage":"0","varName":"","reason":"Command message","name":"Delete Message"}],"_aliases":[]},{"name":"ao981","permissions":"NONE","restriction":"0","_id":"jJzpB","actions":[{"title":"***GTA5RP | TOXIC FAMILY***","author":"","color":"00FF3B","url":"","authorIcon":"","authorUrl":"","imageUrl":"","thumbUrl":"","timestamp":"true","debug":"false","text":"","year":"","month":"","day":"","hour":"","minute":"","second":"","storage":"1","varName":"emb1","name":"Create Embed Message"},{"storage":"1","varName":"emb1","fieldName":"**Отчёт по автомобилю**","message":":small_orange_diamond:  Тег участника: ${member}\n:small_orange_diamond:  Взятый автомобиль: *Infiniti FX50S (__YF981NUD__)*","inline":"1","name":"Add Embed Field"},{"storage":"1","varName":"emb1","channel":"6","varName2":"cars","storage3":"0","varName3":"","iffalse":"0","iffalseVal":"","messageContent":"","name":"Send Embed Message"},{"storage":"0","varName":"","reason":"Command message","name":"Delete Message"}],"_aliases":[]},{"name":"ao122","permissions":"NONE","restriction":"0","_id":"jJzpB","actions":[{"title":"***GTA5RP | TOXIC FAMILY***","author":"","color":"00FF3B","url":"","authorIcon":"","authorUrl":"","imageUrl":"","thumbUrl":"","timestamp":"true","debug":"false","text":"","year":"","month":"","day":"","hour":"","minute":"","second":"","storage":"1","varName":"emb1","name":"Create Embed Message"},{"storage":"1","varName":"emb1","fieldName":"**Отчёт по автомобилю**","message":":small_orange_diamond:  Тег участника: ${member}\n:small_orange_diamond:  Взятый автомобиль: *Infiniti FX50S (__HA122WNC__)*","inline":"1","name":"Add Embed Field"},{"storage":"1","varName":"emb1","channel":"6","varName2":"cars","storage3":"0","varName3":"","iffalse":"0","iffalseVal":"","messageContent":"","name":"Send Embed Message"},{"storage":"0","varName":"","reason":"Command message","name":"Delete Message"}],"_aliases":[]},{"name":"rolelist","permissions":"ADMINISTRATOR","restriction":"1","_id":"LPHCS","actions":[{"channel":"0","varName":"","message":"*Список ролей:*\n${serverVars(\"rang1\")}\n${serverVars(\"rang2\")}\n${serverVars(\"rang3\")}\n${serverVars(\"rang4\")}\n${serverVars(\"rang5\")}\n${serverVars(\"rang6\")}\n${serverVars(\"rang7\")}\n${serverVars(\"rang8\")}\n${serverVars(\"rang9\")}\n${serverVars(\"high-rang\")}\n${serverVars(\"toxic-role\")}\n${serverVars(\"friend-role\")}\n${serverVars(\"star-role\")}","storage":"0","varName2":"","iffalse":"0","iffalseVal":"","name":"Send Message"},{"channel":"0","varName":"","info":"0","search":"Список ролей:","storage":"1","varName2":"mes","name":"Find Message"},{"storage":"0","varName":"","reason":"","name":"Delete Message"},{"time":"5","measurement":"1","name":"Wait"},{"storage":"1","varName":"mes","reason":"","name":"Delete Message"}]},{"name":"invite","permissions":"MANAGE_ROLES","restriction":"1","_id":"JaDLV","actions":[{"storage":"0","varName":"","reason":"command message","name":"Delete Message"},{"condition":"1","comparison":"0","value":"1","iftrue":"0","iftrueVal":"6","iffalse":"2","iffalseVal":"4","name":"Check Parameters"},{"condition":"0","comparison":"3","value":"2","iftrue":"2","iftrueVal":"8","iffalse":"0","iffalseVal":"6","name":"Check Parameters"},{"title":"***GTA5RP | TOXIC FAMILY***","author":"","color":"00FF3B","url":"","authorIcon":"","authorUrl":"","imageUrl":"","thumbUrl":"","timestamp":"true","debug":"false","text":"","year":"","month":"","day":"","hour":"","minute":"","second":"","storage":"1","varName":"emb1","name":"Create Embed Message"},{"storage":"1","varName":"emb1","fieldName":":x:  **В команде допущена ошибка!**","message":"Верное использование команды: *-invite <@Участник> <Ник в игре>*","inline":"1","name":"Add Embed Field"},{"storage":"1","varName":"emb1","channel":"6","varName2":"bot-logs","storage3":"0","varName3":"","iffalse":"0","iffalseVal":"","messageContent":"","name":"Send Embed Message"},{"name":"End Action Sequence"},{"channel":"6","varName":"bot-logs","message":":warning:  Загрузка...","storage":"1","varName2":"loading-mes","iffalse":"0","iffalseVal":"","name":"Send Message"},{"info":"2","infoIndex":"1","storage":"1","varName":"member","name":"Store Command Params"},{"info":"1","infoIndex":"2","storage":"1","varName":"nickname","name":"Store Command Params"},{"title":"***GTA5RP | TOXIC FAMILY***","author":"","color":"00FF3B","url":"","authorIcon":"","authorUrl":"","imageUrl":"","thumbUrl":"","timestamp":"true","debug":"false","text":"","year":"","month":"","day":"","hour":"","minute":"","second":"","storage":"1","varName":"emb2","name":"Create Embed Message"},{"storage":"1","varName":"emb2","fieldName":":white_check_mark:  **Заявка одобрена!**","message":":heart: *Ваша заявка в семью TOXIC была успешно одобрена! Добро пожаловать!*","inline":"1","name":"Add Embed Field"},{"storage":"1","varName":"emb2","channel":"2","varName2":"bot-logs","storage3":"0","varName3":"","iffalse":"0","iffalseVal":"","messageContent":"","name":"Send Embed Message"},{"member":"0","varName":"","nickname":"${tempVars(\"nickname\")}","reason":"Одобренная заявка в семью","name":"Set Member Nickname"},{"member":"0","varName2":"","role":"4","varName":"friend-role","reason":"Одобренная заявка в семью.","name":"Remove Member Role"},{"member":"0","varName2":"","role":"4","varName":"star-role","reason":"Одобренная заявка в семью.","name":"Remove Member Role"},{"member":"0","varName2":"","role":"4","varName":"rang1","reason":"Одобренная заявка в семью.","name":"Add Member Role"},{"member":"0","varName2":"","role":"4","varName":"toxic-role","reason":"Одобренная заявка в семью.","name":"Add Member Role"},{"storage":"1","varName":"loading-mes","reason":"","name":"Delete Message"},{"title":"***GTA5RP | TOXIC FAMILY***","author":"","color":"00FF3B","url":"","authorIcon":"","authorUrl":"","imageUrl":"","thumbUrl":"","timestamp":"true","debug":"false","text":"","year":"","month":"","day":"","hour":"","minute":"","second":"","storage":"1","varName":"emb3","name":"Create Embed Message"},{"storage":"1","varName":"emb3","fieldName":":white_check_mark:  **Заявка одобрена!**","message":":heart: Заявка ${mentionedUser} в семью была успешно одобрена!\n*// by ${member}*","inline":"1","name":"Add Embed Field"},{"storage":"1","varName":"emb3","channel":"6","varName2":"bot-logs","storage3":"0","varName3":"","iffalse":"0","iffalseVal":"","messageContent":"","name":"Send Embed Message"}]},{"name":"kick","permissions":"MANAGE_ROLES","restriction":"1","_id":"JaDLV","actions":[{"storage":"0","varName":"","reason":"command message","name":"Delete Message"},{"condition":"1","comparison":"0","value":"1","iftrue":"0","iftrueVal":"6","iffalse":"2","iffalseVal":"4","name":"Check Parameters"},{"condition":"0","comparison":"3","value":"2","iftrue":"2","iftrueVal":"8","iffalse":"0","iffalseVal":"6","name":"Check Parameters"},{"title":"***GTA5RP | TOXIC FAMILY***","author":"","color":"00FF3B","url":"","authorIcon":"","authorUrl":"","imageUrl":"","thumbUrl":"","timestamp":"true","debug":"false","text":"","year":"","month":"","day":"","hour":"","minute":"","second":"","storage":"1","varName":"emb1","name":"Create Embed Message"},{"storage":"1","varName":"emb1","fieldName":":x:  **В команде допущена ошибка!**","message":"Верное использование команды: *-kick <@Участник> <Причина>*","inline":"1","name":"Add Embed Field"},{"storage":"1","varName":"emb1","channel":"6","varName2":"bot-logs","storage3":"0","varName3":"","iffalse":"0","iffalseVal":"","messageContent":"","name":"Send Embed Message"},{"name":"End Action Sequence"},{"channel":"6","varName":"bot-logs","message":":warning:  Загрузка...","storage":"1","varName2":"loading-mes","iffalse":"0","iffalseVal":"","name":"Send Message"},{"info":"2","infoIndex":"1","storage":"1","varName":"member","name":"Store Command Params"},{"info":"1","infoIndex":"2","storage":"1","varName":"reason","name":"Store Command Params"},{"title":"***GTA5RP | TOXIC FAMILY***","author":"","color":"00FF3B","url":"","authorIcon":"","authorUrl":"","imageUrl":"","thumbUrl":"","timestamp":"true","debug":"false","text":"","year":"","month":"","day":"","hour":"","minute":"","second":"","storage":"1","varName":"emb2","name":"Create Embed Message"},{"storage":"1","varName":"emb2","fieldName":":bangbang:  **Изгнание!**","message":":disappointed_relieved: *Вы были изгнаны из GTA5RP семьи TOXIC!*\n:question: Причина: **__${tempVars(\"reason\")}__**","inline":"1","name":"Add Embed Field"},{"storage":"1","varName":"emb2","channel":"2","varName2":"bot-logs","storage3":"0","varName3":"","iffalse":"0","iffalseVal":"","messageContent":"","name":"Send Embed Message"},{"member":"0","varName2":"","role":"4","varName":"toxic-role","reason":"Изгнание из семьи. Причина: ${tempVars(\"reason\")}","name":"Remove Member Role"},{"member":"0","varName2":"","role":"4","varName":"rang1","reason":"Изгнание из семьи. Причина: ${tempVars(\"reason\")}","name":"Remove Member Role"},{"member":"0","varName2":"","role":"4","varName":"rang2","reason":"Изгнание из семьи. Причина: ${tempVars(\"reason\")}","name":"Remove Member Role"},{"member":"0","varName2":"","role":"4","varName":"rang3","reason":"Изгнание из семьи. Причина: ${tempVars(\"reason\")}","name":"Remove Member Role"},{"member":"0","varName2":"","role":"4","varName":"rang4","reason":"Изгнание из семьи. Причина: ${tempVars(\"reason\")}","name":"Remove Member Role"},{"member":"0","varName2":"","role":"4","varName":"rang5","reason":"Изгнание из семьи. Причина: ${tempVars(\"reason\")}","name":"Remove Member Role"},{"member":"0","varName2":"","role":"4","varName":"rang6","reason":"Изгнание из семьи. Причина: ${tempVars(\"reason\")}","name":"Remove Member Role"},{"member":"0","varName2":"","role":"4","varName":"rang7","reason":"Изгнание из семьи. Причина: ${tempVars(\"reason\")}","name":"Remove Member Role"},{"member":"0","varName2":"","role":"4","varName":"rang8","reason":"Изгнание из семьи. Причина: ${tempVars(\"reason\")}","name":"Remove Member Role"},{"member":"0","varName2":"","role":"4","varName":"rang9","reason":"Изгнание из семьи. Причина: ${tempVars(\"reason\")}","name":"Remove Member Role"},{"member":"0","varName2":"","role":"4","varName":"high-rang","reason":"Изгнание из семьи. Причина: ${tempVars(\"reason\")}","name":"Remove Member Role"},{"member":"0","varName2":"","role":"4","varName":"friend-role","reason":"Изгнание из семьи. Причина: ${tempVars(\"reason\")}","name":"Add Member Role"},{"storage":"1","varName":"loading-mes","reason":"","name":"Delete Message"},{"title":"***GTA5RP | TOXIC FAMILY***","author":"","color":"00FF3B","url":"","authorIcon":"","authorUrl":"","imageUrl":"","thumbUrl":"","timestamp":"true","debug":"false","text":"","year":"","month":"","day":"","hour":"","minute":"","second":"","storage":"1","varName":"emb3","name":"Create Embed Message"},{"storage":"1","varName":"emb3","fieldName":":bangbang:  **Изгнание!**","message":":disappointed_relieved: *${member} изгнал ${mentionedUser} из семьи TOXIC!*\n:question: Причина: **__${tempVars(\"reason\")}__**","inline":"1","name":"Add Embed Field"},{"storage":"1","varName":"emb3","channel":"6","varName2":"bot-logs","storage3":"0","varName3":"","iffalse":"0","iffalseVal":"","messageContent":"","name":"Send Embed Message"}]},{"name":"blacklist","permissions":"MANAGE_ROLES","restriction":"1","_id":"JaDLV","actions":[{"storage":"0","varName":"","reason":"command message","name":"Delete Message"},{"condition":"1","comparison":"0","value":"1","iftrue":"0","iftrueVal":"6","iffalse":"2","iffalseVal":"4","name":"Check Parameters"},{"condition":"0","comparison":"3","value":"3","iftrue":"2","iftrueVal":"8","iffalse":"0","iffalseVal":"6","name":"Check Parameters"},{"title":"***GTA5RP | TOXIC FAMILY***","author":"","color":"00FF3B","url":"","authorIcon":"","authorUrl":"","imageUrl":"","thumbUrl":"","timestamp":"true","debug":"false","text":"","year":"","month":"","day":"","hour":"","minute":"","second":"","storage":"1","varName":"emb1","name":"Create Embed Message"},{"storage":"1","varName":"emb1","fieldName":":x:  **В команде допущена ошибка!**","message":"Верное использование команды: *-blacklist <@Участник> <Номер паспорта> <Причина>*","inline":"1","name":"Add Embed Field"},{"storage":"1","varName":"emb1","channel":"6","varName2":"bot-logs","storage3":"0","varName3":"","iffalse":"0","iffalseVal":"","messageContent":"","name":"Send Embed Message"},{"name":"End Action Sequence"},{"channel":"6","varName":"bot-logs","message":":warning:  Загрузка...","storage":"1","varName2":"loading-mes","iffalse":"0","iffalseVal":"","name":"Send Message"},{"info":"2","infoIndex":"1","storage":"1","varName":"member","name":"Store Command Params"},{"info":"0","infoIndex":"2","storage":"1","varName":"pass","name":"Store Command Params"},{"info":"1","infoIndex":"3","storage":"1","varName":"reason","name":"Store Command Params"},{"member":"0","varName":"","info":"3","storage":"1","varName2":"nickname","name":"Store Member Info"},{"member":"1","varName":"","info":"3","storage":"1","varName2":"cmdname","name":"Store Member Info"},{"title":"***GTA5RP | TOXIC FAMILY***","author":"","color":"00FF3B","url":"","authorIcon":"","authorUrl":"","imageUrl":"","thumbUrl":"","timestamp":"true","debug":"false","text":"","year":"","month":"","day":"","hour":"","minute":"","second":"","storage":"1","varName":"emb2","name":"Create Embed Message"},{"storage":"1","varName":"emb2","fieldName":":bangbang:  **Информация**","message":":disappointed_relieved: *Вас внесли в __черный список__ GTA5RP семьи TOXIC!*\n:question: Причина: **__${tempVars(\"reason\")}__**","inline":"1","name":"Add Embed Field"},{"storage":"1","varName":"emb2","channel":"2","varName2":"bot-logs","storage3":"0","varName3":"","iffalse":"0","iffalseVal":"","messageContent":"","name":"Send Embed Message"},{"title":"***GTA5RP | TOXIC FAMILY***","author":"","color":"00FF3B","url":"","authorIcon":"","authorUrl":"","imageUrl":"","thumbUrl":"","timestamp":"true","debug":"false","text":"","year":"","month":"","day":"","hour":"","minute":"","second":"","storage":"1","varName":"emb3","name":"Create Embed Message"},{"storage":"1","varName":"emb3","fieldName":":no_entry_sign:  **Черный список**","message":":small_orange_diamond:  Тег исполнителя: **${member}**\n:small_orange_diamond:  Никнейм занесенного в ЧС: **${tempVars(\"nickname\")}**\n:small_orange_diamond:  Тег занесенного в ЧС: **${mentionedUser}**\n:small_orange_diamond:  Номер паспорта занесенного в ЧС: **${tempVars(\"pass\")}**\n:small_orange_diamond:  Причина: **${tempVars(\"reason\")}**","inline":"1","name":"Add Embed Field"},{"storage":"1","varName":"emb3","channel":"6","varName2":"blacklist","storage3":"0","varName3":"","iffalse":"0","iffalseVal":"","messageContent":"","name":"Send Embed Message"},{"storage":"1","varName":"loading-mes","reason":"","name":"Delete Message"},{"title":"***GTA5RP | TOXIC FAMILY***","author":"","color":"00FF3B","url":"","authorIcon":"","authorUrl":"","imageUrl":"","thumbUrl":"","timestamp":"true","debug":"false","text":"","year":"","month":"","day":"","hour":"","minute":"","second":"","storage":"1","varName":"emb4","name":"Create Embed Message"},{"storage":"1","varName":"emb4","fieldName":":bangbang:  **Внесение в черный список!**","message":":disappointed_relieved: *${member} внес в черный список ${mentionedUser} (${tempVars(\"nickname\")}) семьи TOXIC!*\n:question: Причина: **__${tempVars(\"reason\")}__**","inline":"1","name":"Add Embed Field"},{"storage":"1","varName":"emb4","channel":"6","varName2":"bot-logs","storage3":"0","varName3":"","iffalse":"0","iffalseVal":"","messageContent":"","name":"Send Embed Message"},{"member":"0","varName":"","reason":"Черный Список // by ${tempVars(\"cmdname\")}","guild":"0","varName2":"","days":"","name":"Ban Member"}]}]